setup.py
src/loggingd/__init__.py
src/loggingd/config.py
src/loggingd/decorators.py
src/loggingd/util.py
src/loggingd.egg-info/PKG-INFO
src/loggingd.egg-info/SOURCES.txt
src/loggingd.egg-info/dependency_links.txt
src/loggingd.egg-info/requires.txt
src/loggingd.egg-info/top_level.txt