Metadata-Version: 1.1
Name: loggingd
Version: 1.4
Summary: Logging framework using decorators.
Home-page: https://github.com/cooledcoffee/loggingd
Author: Mengchen LEE
Author-email: CooledCoffee@gmail.com
License: UNKNOWN
Platform: UNKNOWN
Classifier: Development Status :: 4 - Beta
Classifier: Intended Audience :: Developers
Classifier: Operating System :: OS Independent
Classifier: Programming Language :: Python
Classifier: Programming Language :: Python :: 2
Classifier: Programming Language :: Python :: 3
Classifier: Topic :: Software Development :: Libraries
Classifier: Topic :: System :: Logging
